{"@t":"2023-11-24T06:23:54.1995228Z","@mt":"Now listening on: {address}","address":"https://localhost:7119","EventId":{"Id":14,"Name":"ListeningOnAddress"},"SourceContext":"Microsoft.Hosting.Lifetime","Application":"Sample"}
{"@t":"2023-11-24T06:23:54.2345988Z","@mt":"Now listening on: {address}","address":"http://localhost:5115","EventId":{"Id":14,"Name":"ListeningOnAddress"},"SourceContext":"Microsoft.Hosting.Lifetime","Application":"Sample"}
{"@t":"2023-11-24T06:23:54.2376812Z","@mt":"Application started. Press Ctrl+C to shut down.","SourceContext":"Microsoft.Hosting.Lifetime","Application":"Sample"}
{"@t":"2023-11-24T06:23:54.2382267Z","@mt":"Hosting environment: {envName}","envName":"Development","SourceContext":"Microsoft.Hosting.Lifetime","Application":"Sample"}
{"@t":"2023-11-24T06:23:54.2382783Z","@mt":"Content root path: {contentRoot}","contentRoot":"C:\\Users\\sam\\Desktop\\FullStackDevelopment\\SudentMgnt\\backend\\StudentDemo\\Student.API\\","SourceContext":"Microsoft.Hosting.Lifetime","Application":"Sample"}
{"@t":"2023-11-24T06:23:54.4735178Z","@mt":"{HostingRequestStartingLog:l}","@r":["Request starting HTTP/2 GET https://localhost:7119/swagger/index.html - -"],"Protocol":"HTTP/2","Method":"GET","ContentType":null,"ContentLength":null,"Scheme":"https","Host":"localhost:7119","PathBase":"","Path":"/swagger/index.html","QueryString":"","HostingRequestStartingLog":"Request starting HTTP/2 GET https://localhost:7119/swagger/index.html - -","EventId":{"Id":1},"SourceContext":"Microsoft.AspNetCore.Hosting.Diagnostics","RequestId":"0HMVCMNNC42PS:00000001","RequestPath":"/swagger/index.html","ConnectionId":"0HMVCMNNC42PS","Application":"Sample"}
{"@t":"2023-11-24T06:23:54.8908406Z","@mt":"{HostingRequestStartingLog:l}","@r":["Request starting HTTP/2 GET https://localhost:7119/_framework/aspnetcore-browser-refresh.js - -"],"Protocol":"HTTP/2","Method":"GET","ContentType":null,"ContentLength":null,"Scheme":"https","Host":"localhost:7119","PathBase":"","Path":"/_framework/aspnetcore-browser-refresh.js","QueryString":"","HostingRequestStartingLog":"Request starting HTTP/2 GET https://localhost:7119/_framework/aspnetcore-browser-refresh.js - -","EventId":{"Id":1},"SourceContext":"Microsoft.AspNetCore.Hosting.Diagnostics","RequestId":"0HMVCMNNC42PS:00000003","RequestPath":"/_framework/aspnetcore-browser-refresh.js","ConnectionId":"0HMVCMNNC42PS","Application":"Sample"}
{"@t":"2023-11-24T06:23:54.8908846Z","@mt":"{HostingRequestStartingLog:l}","@r":["Request starting HTTP/2 GET https://localhost:7119/_vs/browserLink - -"],"Protocol":"HTTP/2","Method":"GET","ContentType":null,"ContentLength":null,"Scheme":"https","Host":"localhost:7119","PathBase":"","Path":"/_vs/browserLink","QueryString":"","HostingRequestStartingLog":"Request starting HTTP/2 GET https://localhost:7119/_vs/browserLink - -","EventId":{"Id":1},"SourceContext":"Microsoft.AspNetCore.Hosting.Diagnostics","RequestId":"0HMVCMNNC42PS:00000005","RequestPath":"/_vs/browserLink","ConnectionId":"0HMVCMNNC42PS","Application":"Sample"}
{"@t":"2023-11-24T06:23:54.8961611Z","@mt":"{HostingRequestFinishedLog:l}","@r":["Request finished HTTP/2 GET https://localhost:7119/swagger/index.html - - - 200 - text/html;charset=utf-8 426.6184ms"],"ElapsedMilliseconds":426.6184,"StatusCode":200,"ContentType":"text/html;charset=utf-8","ContentLength":null,"Protocol":"HTTP/2","Method":"GET","Scheme":"https","Host":"localhost:7119","PathBase":"","Path":"/swagger/index.html","QueryString":"","HostingRequestFinishedLog":"Request finished HTTP/2 GET https://localhost:7119/swagger/index.html - - - 200 - text/html;charset=utf-8 426.6184ms","EventId":{"Id":2},"SourceContext":"Microsoft.AspNetCore.Hosting.Diagnostics","RequestId":"0HMVCMNNC42PS:00000001","RequestPath":"/swagger/index.html","ConnectionId":"0HMVCMNNC42PS","Application":"Sample"}
{"@t":"2023-11-24T06:23:54.9095066Z","@mt":"{HostingRequestFinishedLog:l}","@r":["Request finished HTTP/2 GET https://localhost:7119/_framework/aspnetcore-browser-refresh.js - - - 200 12354 application/javascript;+charset=utf-8 18.5484ms"],"ElapsedMilliseconds":18.5484,"StatusCode":200,"ContentType":"application/javascript; charset=utf-8","ContentLength":12354,"Protocol":"HTTP/2","Method":"GET","Scheme":"https","Host":"localhost:7119","PathBase":"","Path":"/_framework/aspnetcore-browser-refresh.js","QueryString":"","HostingRequestFinishedLog":"Request finished HTTP/2 GET https://localhost:7119/_framework/aspnetcore-browser-refresh.js - - - 200 12354 application/javascript;+charset=utf-8 18.5484ms","EventId":{"Id":2},"SourceContext":"Microsoft.AspNetCore.Hosting.Diagnostics","RequestId":"0HMVCMNNC42PS:00000003","RequestPath":"/_framework/aspnetcore-browser-refresh.js","ConnectionId":"0HMVCMNNC42PS","Application":"Sample"}
{"@t":"2023-11-24T06:23:54.9222765Z","@mt":"{HostingRequestFinishedLog:l}","@r":["Request finished HTTP/2 GET https://localhost:7119/_vs/browserLink - - - 200 - text/javascript;+charset=UTF-8 31.3301ms"],"ElapsedMilliseconds":31.3301,"StatusCode":200,"ContentType":"text/javascript; charset=UTF-8","ContentLength":null,"Protocol":"HTTP/2","Method":"GET","Scheme":"https","Host":"localhost:7119","PathBase":"","Path":"/_vs/browserLink","QueryString":"","HostingRequestFinishedLog":"Request finished HTTP/2 GET https://localhost:7119/_vs/browserLink - - - 200 - text/javascript;+charset=UTF-8 31.3301ms","EventId":{"Id":2},"SourceContext":"Microsoft.AspNetCore.Hosting.Diagnostics","RequestId":"0HMVCMNNC42PS:00000005","RequestPath":"/_vs/browserLink","ConnectionId":"0HMVCMNNC42PS","Application":"Sample"}
{"@t":"2023-11-24T06:23:55.0243121Z","@mt":"{HostingRequestStartingLog:l}","@r":["Request starting HTTP/2 GET https://localhost:7119/swagger/v1/swagger.json - -"],"Protocol":"HTTP/2","Method":"GET","ContentType":null,"ContentLength":null,"Scheme":"https","Host":"localhost:7119","PathBase":"","Path":"/swagger/v1/swagger.json","QueryString":"","HostingRequestStartingLog":"Request starting HTTP/2 GET https://localhost:7119/swagger/v1/swagger.json - -","EventId":{"Id":1},"SourceContext":"Microsoft.AspNetCore.Hosting.Diagnostics","RequestId":"0HMVCMNNC42PS:00000007","RequestPath":"/swagger/v1/swagger.json","ConnectionId":"0HMVCMNNC42PS","Application":"Sample"}
{"@t":"2023-11-24T06:23:55.2007252Z","@mt":"{HostingRequestFinishedLog:l}","@r":["Request finished HTTP/2 GET https://localhost:7119/swagger/v1/swagger.json - - - 200 - application/json;charset=utf-8 176.4002ms"],"ElapsedMilliseconds":176.4002,"StatusCode":200,"ContentType":"application/json;charset=utf-8","ContentLength":null,"Protocol":"HTTP/2","Method":"GET","Scheme":"https","Host":"localhost:7119","PathBase":"","Path":"/swagger/v1/swagger.json","QueryString":"","HostingRequestFinishedLog":"Request finished HTTP/2 GET https://localhost:7119/swagger/v1/swagger.json - - - 200 - application/json;charset=utf-8 176.4002ms","EventId":{"Id":2},"SourceContext":"Microsoft.AspNetCore.Hosting.Diagnostics","RequestId":"0HMVCMNNC42PS:00000007","RequestPath":"/swagger/v1/swagger.json","ConnectionId":"0HMVCMNNC42PS","Application":"Sample"}
